Metadata-Version: 2.1
Name: first-book
Version: 1.1.1
Summary: A Python library for test first books
Home-page: https://github.com/kovalevskiy/first_book
Download-URL: https://github.com/kovalevskiy
Author: Rudolf Kovalevskiy
Author-email: kovalevskiy2017@outlook.com
License: MIT
